check_inputs
