Metadata-Version: 1.0
Name: CheckInputs
Version: 1.2
Summary: Check input values for laboratory works.
Home-page: UNKNOWN
Author: Alexey Garmash
Author-email: kshatan03@gmail.com
License: UNKNOWN
Platform: UNKNOWN
